MANIFEST.in
README.md
requirements.txt
setup.py
chunk_segmentor/__init__.py
chunk_segmentor/model.py
chunk_segmentor/preprocessing.py
chunk_segmentor/segment.py
chunk_segmentor/tagger.py
chunk_segmentor/trie.py
chunk_segmentor/utils.py
chunk_segmentor.egg-info/PKG-INFO
chunk_segmentor.egg-info/SOURCES.txt
chunk_segmentor.egg-info/dependency_links.txt
chunk_segmentor.egg-info/requires.txt
chunk_segmentor.egg-info/top_level.txt
chunk_segmentor/segmentor/__init__.py
chunk_segmentor/segmentor/static/hanlp-test-1.6.7.jar
chunk_segmentor/segmentor/static/hanlp.properties