Metadata-Version: 1.2
Name: chunk-segmentor
Version: 1.1.0
Summary: Segmentor with Noun Pharses
Home-page: https://github.com/stevewyl/chunk_segmentor
Author: yilei.wang
Author-email: stevewyl@163.com
License: MIT
Platform: UNKNOWN
Classifier: Programming Language :: Python
Classifier: Programming Language :: Python :: 3.6
Classifier: Programming Language :: Python :: Implementation :: CPython
Classifier: Programming Language :: Python :: Implementation :: PyPy
Classifier: Programming Language :: Java
Requires-Python: >=3.6
